algozar/__init__.py
algozar/print.py
algozar/sorting/__init__.py
algozar/sorting/bubble_sort.py
algozar/sorting/linear_search.py
algozar/sorting/quick_sort.py
algozar-0.1.0.dist-info/METADATA
algozar-0.1.0.dist-info/WHEEL
algozar-0.1.0.dist-info/top_level.txt
algozar-0.1.0.dist-info/RECORD
